cookbook/__init__.py
cookbook/config.py
cookbook/cookbook.py
cookbook/main.py
cookbook/utils.py
djelia/__init__.py
djelia/config/__init__.py
djelia/config/settings.py
djelia/models/__init__.py
djelia/models/models.py
djelia/src/__init__.py
djelia/src/auth/__init__.py
djelia/src/auth/auth.py
djelia/src/client/__init__.py
djelia/src/client/client.py
djelia/src/services/__init__.py
djelia/src/services/transcription.py
djelia/src/services/translation.py
djelia/src/services/tts.py
djelia/utils/__init__.py
djelia/utils/errors.py
djelia/utils/exceptions.py
djelia/utils/logger.py
djelia/utils/utils.py
djelia-1.1.1.dist-info/licenses/LICENSE
djelia-1.1.1.dist-info/METADATA
djelia-1.1.1.dist-info/WHEEL
djelia-1.1.1.dist-info/top_level.txt
djelia-1.1.1.dist-info/RECORD
