Metadata-Version: 2.4
Name: djelia
Version: 1.1.1
Summary: Djelia Python SDK - Advanced AI for African Languages
Home-page: https://github.com/djelia-org/djelia-python-sdk
Author: Djelia
Author-email: support@djelia.cloud
Project-URL: Bug Tracker, https://github.com/djelia-org/djelia-python-sdk/issues
Project-URL: Documentation, https://djelia.cloud/docs
Project-URL: Source Code, https://github.com/djelia-org/djelia-python-sdk
Project-URL: Homepage, https://djelia.cloud
Keywords: djelia,nlp,translation,transcription,text-to-speech,tts,african languages,bambara,mali,async,ai,machine learning,speech recognition,voice synthesis,multilingual,linguistics
Classifier: Development Status :: 4 - Beta
Classifier: Intended Audience :: Developers
Classifier: Topic :: Software Development :: Libraries :: Python Modules
Classifier: Topic :: Text Processing :: Linguistic
Classifier: Topic :: Scientific/Engineering :: Artificial Intelligence
Classifier: Topic :: Multimedia :: Sound/Audio :: Speech
Classifier: License :: OSI Approved :: MIT License
Classifier: Programming Language :: Python :: 3
Classifier: Programming Language :: Python :: 3.7
Classifier: Programming Language :: Python :: 3.8
Classifier: Programming Language :: Python :: 3.9
Classifier: Programming Language :: Python :: 3.10
Classifier: Programming Language :: Python :: 3.11
Classifier: Programming Language :: Python :: 3.12
Classifier: Operating System :: OS Independent
Requires-Python: >=3.7
License-File: LICENSE
Requires-Dist: requests>=2.25.0
Requires-Dist: aiohttp>=3.8.0
Requires-Dist: pydantic-settings>=2.10.1
Requires-Dist: pydantic>=2.7.0
Requires-Dist: tenacity>=9.1.2
Provides-Extra: dev
Requires-Dist: pytest>=6.0; extra == "dev"
Requires-Dist: pytest-asyncio>=0.18.0; extra == "dev"
Requires-Dist: black>=21.0.0; extra == "dev"
Requires-Dist: flake8>=3.9.0; extra == "dev"
Requires-Dist: mypy>=0.910; extra == "dev"
Requires-Dist: isort>=5.0.0; extra == "dev"
Requires-Dist: ruff>=0.11.4; extra == "dev"
Requires-Dist: pre-commit>=2.15.0; extra == "dev"
Provides-Extra: docs
Requires-Dist: sphinx>=4.0.0; extra == "docs"
Requires-Dist: sphinx-rtd-theme>=0.5.0; extra == "docs"
Provides-Extra: test
Requires-Dist: pytest>=6.0; extra == "test"
Requires-Dist: pytest-asyncio>=0.18.0; extra == "test"
Requires-Dist: python-dotenv>=0.19.0; extra == "test"
Dynamic: author
Dynamic: author-email
Dynamic: classifier
Dynamic: description
Dynamic: description-content-type
Dynamic: home-page
Dynamic: keywords
Dynamic: license-file
Dynamic: project-url
Dynamic: provides-extra
Dynamic: requires-dist
Dynamic: requires-python
Dynamic: summary
